[{"match_id": "15265271", "target": "q3", "date": "2026-04-10", "league": "Argentina Liga Nacional", "volatility": 0.123, "gender": "men", "pace_bucket": "fast", "confidence": 0.6844, "winner_pick": "home", "target_winner": "home", "hit": true, "outcome": "hit"}, {"match_id": "15265271", "target": "q4", "date": "2026-04-10", "league": "Argentina Liga Nacional", "volatility": 0.098, "gender": "men", "pace_bucket": "fast", "confidence": 0.7001, "winner_pick": "home", "target_winner": "home", "hit": true, "outcome": "hit"}, {"match_id": "15265270", "target": "q4", "date": "2026-04-10", "league": "Argentina Liga Nacional", "volatility": 0.141, "gender": "men", "pace_bucket": "medium", "confidence": 0.9137, "winner_pick": "home", "target_winner": "home", "hit": true, "outcome": "hit"}, {"match_id": "15903482", "target": "q3", "date": "2026-04-10", "league": "Superliga", "volatility": 0.202, "gender": "men", "pace_bucket": "medium", "confidence": 0.7307, "winner_pick": "away", "target_winner": "away", "hit": true, "outcome": "hit"}, {"match_id": "15899092", "target": "q3", "date": "2026-04-10", "league": "Superliga", "volatility": 0.261, "gender": "men", "pace_bucket": "medium", "confidence": 0.7184, "winner_pick": "home", "target_winner": "home", "hit": true, "outcome": "hit"}, {"match_id": "15899092", "target": "q4", "date": "2026-04-10", "league": "Superliga", "volatility": 0.108, "gender": "men", "pace_bucket": "fast", "confidence": 0.9404, "winner_pick": "home", "target_winner": "away", "hit": false, "outcome": "miss"}, {"match_id": "15203019", "target": "q4", "date": "2026-04-10", "league": "Brazil NBB", "volatility": 0.131, "gender": "men", "pace_bucket": "medium", "confidence": 0.826, "winner_pick": "away", "target_winner": "home", "hit": false, "outcome": "miss"}, {"match_id": "14373944", "target": "q4", "date": "2026-04-10", "league": "Primera FEB", "volatility": 0.113, "gender": "men", "pace_bucket": "medium", "confidence": 0.9499, "winner_pick": "away", "target_winner": "away", "hit": true, "outcome": "hit"}, {"match_id": "14210796", "target": "q3", "date": "2026-04-10", "league": "Euroleague", "volatility": 0.171, "gender": "men", "pace_bucket": "fast", "confidence": 0.7944, "winner_pick": "home", "target_winner": "home", "hit": true, "outcome": "hit"}, {"match_id": "15597954", "target": "q4", "date": "2026-04-10", "league": "Nationale 1, Relegation Round", "volatility": 0.141, "gender": "men", "pace_bucket": "slow", "confidence": 0.8758, "winner_pick": "away", "target_winner": "away", "hit": true, "outcome": "hit"}, {"match_id": "14272574", "target": "q3", "date": "2026-04-10", "league": "\u00c9lite 2", "volatility": 0.213, "gender": "men", "pace_bucket": "medium", "confidence": 0.7083, "winner_pick": "home", "target_winner": "away", "hit": false, "outcome": "miss"}, {"match_id": "14272574", "target": "q4", "date": "2026-04-10", "league": "\u00c9lite 2", "volatility": 0.094, "gender": "men", "pace_bucket": "medium", "confidence": 0.8851, "winner_pick": "away", "target_winner": "away", "hit": true, "outcome": "hit"}, {"match_id": "14270301", "target": "q3", "date": "2026-04-10", "league": "France Pro A", "volatility": 0.102, "gender": "men", "pace_bucket": "slow", "confidence": 0.7941, "winner_pick": "home", "target_winner": "away", "hit": false, "outcome": "miss"}, {"match_id": "14270301", "target": "q4", "date": "2026-04-10", "league": "France Pro A", "volatility": 0.109, "gender": "men", "pace_bucket": "slow", "confidence": 0.9161, "winner_pick": "home", "target_winner": "home", "hit": true, "outcome": "hit"}, {"match_id": "15597955", "target": "q3", "date": "2026-04-10", "league": "Nationale 1, Relegation Round", "volatility": 0.298, "gender": "men", "pace_bucket": "fast", "confidence": 0.7831, "winner_pick": "away", "target_winner": "away", "hit": true, "outcome": "hit"}, {"match_id": "15597952", "target": "q4", "date": "2026-04-10", "league": "Nationale 1, Relegation Round", "volatility": 0.158, "gender": "men", "pace_bucket": "fast", "confidence": 0.6599, "winner_pick": "away", "target_winner": "away", "hit": true, "outcome": "hit"}, {"match_id": "15597949", "target": "q3", "date": "2026-04-10", "league": "Nationale 1, Relegation Round", "volatility": 0.155, "gender": "men", "pace_bucket": "slow", "confidence": 0.864, "winner_pick": "home", "target_winner": "home", "hit": true, "outcome": "hit"}, {"match_id": "15597854", "target": "q4", "date": "2026-04-10", "league": "Nationale 1, Promotion Round", "volatility": 0.208, "gender": "men", "pace_bucket": "slow", "confidence": 0.7782, "winner_pick": "home", "target_winner": "home", "hit": true, "outcome": "hit"}, {"match_id": "15597853", "target": "q3", "date": "2026-04-10", "league": "Nationale 1, Promotion Round", "volatility": 0.089, "gender": "men", "pace_bucket": "slow", "confidence": 0.6715, "winner_pick": "home", "target_winner": "home", "hit": true, "outcome": "hit"}, {"match_id": "15597852", "target": "q4", "date": "2026-04-10", "league": "Nationale 1, Promotion Round", "volatility": 0.116, "gender": "men", "pace_bucket": "slow", "confidence": 0.6693, "winner_pick": "home", "target_winner": "home", "hit": true, "outcome": "hit"}, {"match_id": "14698338", "target": "q3", "date": "2026-04-10", "league": "Germany BBL", "volatility": 0.134, "gender": "men", "pace_bucket": "fast", "confidence": 0.6645, "winner_pick": "away", "target_winner": "away", "hit": true, "outcome": "hit"}, {"match_id": "14698338", "target": "q4", "date": "2026-04-10", "league": "Germany BBL", "volatility": 0.176, "gender": "men", "pace_bucket": "fast", "confidence": 0.9086, "winner_pick": "home", "target_winner": "home", "hit": true, "outcome": "hit"}, {"match_id": "14272581", "target": "q4", "date": "2026-04-10", "league": "\u00c9lite 2", "volatility": 0.197, "gender": "men", "pace_bucket": "fast", "confidence": 0.6801, "winner_pick": "away", "target_winner": "away", "hit": true, "outcome": "hit"}, {"match_id": "14272579", "target": "q3", "date": "2026-04-10", "league": "\u00c9lite 2", "volatility": 0.206, "gender": "men", "pace_bucket": "medium", "confidence": 0.6985, "winner_pick": "away", "target_winner": "away", "hit": true, "outcome": "hit"}, {"match_id": "14210795", "target": "q4", "date": "2026-04-10", "league": "Euroleague", "volatility": 0.197, "gender": "men", "pace_bucket": "fast", "confidence": 0.85, "winner_pick": "home", "target_winner": "home", "hit": true, "outcome": "hit"}, {"match_id": "15706638", "target": "q4", "date": "2026-04-10", "league": "Croatian Premier League", "volatility": 0.116, "gender": "men", "pace_bucket": "medium", "confidence": 0.8073, "winner_pick": "away", "target_winner": "away", "hit": true, "outcome": "hit"}, {"match_id": "15445844", "target": "q4", "date": "2026-04-10", "league": "Swedish Basketball Superettan", "volatility": 0.06, "gender": "men", "pace_bucket": "slow", "confidence": 0.8181, "winner_pick": "home", "target_winner": "away", "hit": false, "outcome": "miss"}, {"match_id": "15597948", "target": "q4", "date": "2026-04-10", "league": "Nationale 1, Relegation Round", "volatility": 0.078, "gender": "men", "pace_bucket": "medium", "confidence": 0.6897, "winner_pick": "away", "target_winner": "away", "hit": true, "outcome": "hit"}, {"match_id": "15874960", "target": "q3", "date": "2026-04-10", "league": "Saku I liiga", "volatility": 0.178, "gender": "men", "pace_bucket": "medium", "confidence": 0.8697, "winner_pick": "home", "target_winner": "away", "hit": false, "outcome": "miss"}, {"match_id": "15706622", "target": "q3", "date": "2026-04-10", "league": "Croatian Premier League", "volatility": 0.076, "gender": "men", "pace_bucket": "fast", "confidence": 0.9037, "winner_pick": "home", "target_winner": "home", "hit": true, "outcome": "hit"}, {"match_id": "15696832", "target": "q3", "date": "2026-04-10", "league": " Liga 1 Masculin, Faza II", "volatility": 0.064, "gender": "men", "pace_bucket": "slow", "confidence": 0.8581, "winner_pick": "away", "target_winner": "away", "hit": true, "outcome": "hit"}, {"match_id": "15696832", "target": "q4", "date": "2026-04-10", "league": " Liga 1 Masculin, Faza II", "volatility": 0.044, "gender": "men", "pace_bucket": "slow", "confidence": 0.9108, "winner_pick": "away", "target_winner": "away", "hit": true, "outcome": "hit"}, {"match_id": "15712156", "target": "q3", "date": "2026-04-10", "league": "Sparkasse Prva Liga Zeni", "volatility": 0.075, "gender": "men", "pace_bucket": "slow", "confidence": 0.906, "winner_pick": "away", "target_winner": "away", "hit": true, "outcome": "hit"}, {"match_id": "15696836", "target": "q3", "date": "2026-04-10", "league": " Liga 1 Masculin, Faza II", "volatility": 0.097, "gender": "men", "pace_bucket": "medium", "confidence": 0.7511, "winner_pick": "home", "target_winner": "home", "hit": true, "outcome": "hit"}, {"match_id": "15696836", "target": "q4", "date": "2026-04-10", "league": " Liga 1 Masculin, Faza II", "volatility": 0.075, "gender": "men", "pace_bucket": "medium", "confidence": 0.905, "winner_pick": "home", "target_winner": "home", "hit": true, "outcome": "hit"}, {"match_id": "14554303", "target": "q4", "date": "2026-04-10", "league": "U21 Espoirs Elite", "volatility": 0.145, "gender": "men", "pace_bucket": "slow", "confidence": 0.8265, "winner_pick": "home", "target_winner": "home", "hit": true, "outcome": "hit"}, {"match_id": "14967156", "target": "q4", "date": "2026-04-10", "league": "China CBA", "volatility": 0.154, "gender": "men", "pace_bucket": "fast", "confidence": 0.7099, "winner_pick": "away", "target_winner": "away", "hit": true, "outcome": "hit"}, {"match_id": "14967154", "target": "q3", "date": "2026-04-10", "league": "China CBA", "volatility": 0.108, "gender": "men", "pace_bucket": "fast", "confidence": 0.866, "winner_pick": "home", "target_winner": "home", "hit": true, "outcome": "hit"}, {"match_id": "14967154", "target": "q4", "date": "2026-04-10", "league": "China CBA", "volatility": 0.071, "gender": "men", "pace_bucket": "fast", "confidence": 0.6504, "winner_pick": "home", "target_winner": "home", "hit": true, "outcome": "hit"}, {"match_id": "14967152", "target": "q4", "date": "2026-04-10", "league": "China CBA", "volatility": 0.131, "gender": "men", "pace_bucket": "medium", "confidence": 0.8905, "winner_pick": "away", "target_winner": "away", "hit": true, "outcome": "hit"}, {"match_id": "15781964", "target": "q4", "date": "2026-04-10", "league": "Israeli National League Basketball", "volatility": 0.174, "gender": "men", "pace_bucket": "medium", "confidence": 0.7395, "winner_pick": "home", "target_winner": "away", "hit": false, "outcome": "push"}, {"match_id": "15738183", "target": "q4", "date": "2026-04-10", "league": "Israeli National League Basketball", "volatility": 0.114, "gender": "men", "pace_bucket": "medium", "confidence": 0.8086, "winner_pick": "away", "target_winner": "away", "hit": true, "outcome": "hit"}, {"match_id": "15781967", "target": "q3", "date": "2026-04-10", "league": "Israeli National League Basketball", "volatility": 0.13, "gender": "men", "pace_bucket": "medium", "confidence": 0.6666, "winner_pick": "away", "target_winner": "away", "hit": true, "outcome": "hit"}, {"match_id": "15781966", "target": "q4", "date": "2026-04-10", "league": "Israeli National League Basketball", "volatility": 0.132, "gender": "men", "pace_bucket": "fast", "confidence": 0.6568, "winner_pick": "away", "target_winner": "home", "hit": false, "outcome": "push"}, {"match_id": "15781965", "target": "q4", "date": "2026-04-10", "league": "Israeli National League Basketball", "volatility": 0.231, "gender": "men", "pace_bucket": "fast", "confidence": 0.8533, "winner_pick": "away", "target_winner": "away", "hit": true, "outcome": "hit"}, {"match_id": "15696837", "target": "q3", "date": "2026-04-10", "league": " Liga 1 Masculin, Faza II", "volatility": 0.072, "gender": "men", "pace_bucket": "medium", "confidence": 0.7381, "winner_pick": "home", "target_winner": "home", "hit": true, "outcome": "hit"}, {"match_id": "15704925", "target": "q3", "date": "2026-04-10", "league": "Jedinstvena kadetska liga", "volatility": 0.221, "gender": "men", "pace_bucket": "medium", "confidence": 0.8031, "winner_pick": "away", "target_winner": "away", "hit": true, "outcome": "hit"}, {"match_id": "15704925", "target": "q4", "date": "2026-04-10", "league": "Jedinstvena kadetska liga", "volatility": 0.095, "gender": "men", "pace_bucket": "medium", "confidence": 0.9536, "winner_pick": "away", "target_winner": "away", "hit": true, "outcome": "hit"}, {"match_id": "14272582", "target": "q3", "date": "2026-04-10", "league": "\u00c9lite 2", "volatility": 0.399, "gender": "men", "pace_bucket": "slow", "confidence": 0.665, "winner_pick": "away", "target_winner": "away", "hit": true, "outcome": "hit"}]